NexusPythonWrapper/NexusFilter.py
NexusPythonWrapper/NexusSort.py
NexusPythonWrapper/NexusWrapper.py
NexusPythonWrapper/__init__.py
NexusPythonWrapper/endpoints.py
NexusPythonWrapper/exceptions.py
NexusPythonWrapper/models.py
nexuspythonwrapper-0.0.10.dist-info/licenses/LICENSE.txt
nexuspythonwrapper-0.0.10.dist-info/METADATA
nexuspythonwrapper-0.0.10.dist-info/WHEEL
nexuspythonwrapper-0.0.10.dist-info/entry_points.txt
nexuspythonwrapper-0.0.10.dist-info/top_level.txt
nexuspythonwrapper-0.0.10.dist-info/RECORD
