Metadata-Version: 2.4
Name: NexusPythonWrapper
Version: 0.0.10
Summary: REST API Wrapper library for NEXUS Integrity Centre
Home-page: https://github.com/matthewirvine4/NexusPythonWrapper
Author: Matthew Irvine
Author-email: mattew.irvine44@gmail.com
License: MIT
Project-URL: Source, https://github.com/matthewirvine4/NexusPythonWrapper
Classifier: Development Status :: 3 - Alpha
Classifier: Intended Audience :: Developers
Classifier: License :: OSI Approved :: MIT License
Classifier: Natural Language :: English
Classifier: Operating System :: OS Independent
Classifier: Programming Language :: Python :: 3.13
Classifier: Topic :: Utilities
Requires-Python: >=3.11
License-File: LICENSE.txt
Requires-Dist: requests
Dynamic: author
Dynamic: author-email
Dynamic: classifier
Dynamic: description
Dynamic: description-content-type
Dynamic: home-page
Dynamic: license
Dynamic: license-file
Dynamic: project-url
Dynamic: requires-dist
Dynamic: requires-python
Dynamic: summary
